src/mcp_multilspy/__init__.py
src/mcp_multilspy/server.py
tests/test_server.py
orange_mcp_multilspy-0.1.0.dist-info/METADATA
orange_mcp_multilspy-0.1.0.dist-info/WHEEL
orange_mcp_multilspy-0.1.0.dist-info/entry_points.txt
orange_mcp_multilspy-0.1.0.dist-info/RECORD
