Metadata-Version: 2.4
Name: orange-mcp-multilspy
Version: 0.1.0
Summary: MCP server that exposes Language Server Protocol functionality via multilspy
Author: Asim Ihsan
Requires-Python: >=3.12
Requires-Dist: mcp[cli]>=1.4.1
Requires-Dist: multilspy>=0.0.14
